<employee>
	<empid>1</empid>
	<name>kalyan</name>
	<salary>10000</salary>
	<dept>dev</dept>
</employee>
<employee>
	<empid>2</empid>
	<name>anvith</name>
	<salary>15000</salary>
	<dept>testing</dept>
</employee>
<employee>
	<empid>3</empid>
	<name>raj</name>
	<salary>5000</salary>
	<dept>testing</dept>
</employee>
<employee>
	<empid>4</empid>
	<name>venkat</name>
	<salary>20000</salary>
	<dept>dev</dept>
</employee>
<employee>
	<empid>5</empid>
	<name>soni</name>
	<salary>5000</salary>
	<dept>testing</dept>
</employee>
<employee>
	<empid>6</empid>
	<name>rajesh</name>
	<salary>25000</salary>
	<dept>dev</dept>
</employee>
